zapp/__init__.py
zapp/__main__.py
zapp/cli.py
zapp/core.py
zapp/meta.py
zapp-0.0.7.dist-info/LICENSE.txt
zapp-0.0.7.dist-info/METADATA
zapp-0.0.7.dist-info/WHEEL
zapp-0.0.7.dist-info/entry_points.txt
zapp-0.0.7.dist-info/top_level.txt
zapp-0.0.7.dist-info/RECORD
