Metadata-Version: 2.1
Name: zapp
Version: 0.0.7
Summary: Build zipapp single file Python applications easily
Home-page: https://pypi.org/project/zapp
Author: sinoroc
Author-email: sinoroc.code+python@gmail.com
License: Apache-2.0
Project-URL: GitLab, https://gitlab.com/sinoroc/zapp
Project-URL: GitHub, https://github.com/sinoroc/zapp
Platform: UNKNOWN
Requires-Dist: importlib-metadata
Requires-Dist: setuptools
Requires-Dist: wheel
Provides-Extra: package
Requires-Dist: twine ; extra == 'package'
Requires-Dist: wheel ; extra == 'package'
Provides-Extra: test
Requires-Dist: pytest ; extra == 'test'
Requires-Dist: pytest-pycodestyle ; extra == 'test'
Requires-Dist: pytest-pylint ; extra == 'test'
